setup.cfg
setup.py
class_files/_init_.py
class_files/class_files.py
class_files.egg-info/PKG-INFO
class_files.egg-info/SOURCES.txt
class_files.egg-info/dependency_links.txt
class_files.egg-info/not-zip-safe
class_files.egg-info/top_level.txt