Metadata-Version: 2.1
Name: class-files
Version: 0.3
Summary: Удобный класс для работы с файлами.
Author-email: BusinessJson6@gmail.com
